{
    "book": "골로새서",
    "bookEn": "Colossians",
    "abbr": "Col",
    "chapters": [
        {
            "chapter": 1,
            "verses": [
                {
                    "verse": 1,
                    "text": "하나님의 뜻에 따라 그리스도 예수의 사도가 된 바울과 형제 디모데가"
                },
                {
                    "verse": 2,
                    "text": "골로새에 있는 거룩하고 신실한 그리스도 안에서 형제들에게 우리 하나님 아버지께와 주 예수 그리스도의 은혜와 평화가"
                },
                {
                    "verse": 3,
                    "text": "우리가 너희를 위하여 기도할 때마다 하나님 곧 우리 주 예수 그리스도의 아버지께 늘 감사드리는데"
                },
                {
                    "verse": 4,
                    "text": "이는 우리가 그리스도 예수를 믿는 너희의 믿음과 성도들 모두를 품는 너희의 사랑에 관해 들었기 때문이며"
                },
                {
                    "verse": 5,
                    "text": "또 너희를 위해 하늘에 쌓아둔 소망 때문이다. 이 소망에 관해서는 너희가 전에 진리의 말씀 곧 복음 가운데서 들었거니와"
                },
                {
                    "verse": 6,
                    "text": "그 복음이 마침내 너희에게 이르렀다. 그것이 온 세계에서 열매를 맺고 자라나고 있는 것같이 너희 가운데서도 너희가 진리 안에서 하나님의 은혜를 듣고 깨달은 날로부터 그러하다."
                },
                {
                    "verse": 7,
                    "text": "너희가 우리의 사랑스런 동료 일군 에바브라에게서 그 복음을 배웠거니와 그는 우리를 대표하는 신실한 그리스도의 일군이다."
                },
                {
                    "verse": 8,
                    "text": "또 그가 성령 안에 있는 너희의 사랑을 우리에게 알려 주었다."
                },
                {
                    "verse": 9,
                    "text": "그러므로 우리가 그 소식을 들은 날부터 너희를 위해 끊임없이 기도하되 너희가 온전히 령에 속한 지혜와 지각 가운데서 하나님의 뜻을 아는 지식으로 채우심을 받고"
                },
                {
                    "verse": 10,
                    "text": "주께 합당한 삶을 살아 주를 온전히 기쁘게 하고 모든 선한 행실에 열매를 맺으며 하나님을 온전히 아는 지식이 자라게 해주시기를 간구한다."
                },
                {
                    "verse": 11,
                    "text": "너희가 그의 영광스러운 권능에 의해 모든 능력으로 강해져서 온전히 기쁨에 찬 인내와 오래 참음에 이르러"
                },
                {
                    "verse": 12,
                    "text": "우리로 하여금 빛의 나라에서 성도의 유업을 함께 누리도록 자격을 주신 아버지께 감사드리기 바란다."
                },
                {
                    "verse": 13,
                    "text": "하나님이 우리를 어두움의 권세에서 건져내어 그의 사랑받는 아들의 나라로 옮기셨으니"
                },
                {
                    "verse": 14,
                    "text": "그 아들 안에서 우리가 구속 곧 죄의 사면을 누린다."
                },
                {
                    "verse": 15,
                    "text": "그는 보이지 않는 하나님의 형상이요 만물보다 먼저 나신 이시니"
                },
                {
                    "verse": 16,
                    "text": "그러므로 그분 안에서 하늘이나 땅에 있는 모든 것들 보이는 것들과 보이지 않는 것들 보좌들이나 주권들이나 통치자들이나 권세들이 창조되었으며 만물이 그로 말미암아 그를 위하여 창조되었다."
                },
                {
                    "verse": 17,
                    "text": "또 그는 만물보다 먼저 계시며 만물이 그 안에서 함께 선다."
                },
                {
                    "verse": 18,
                    "text": "또 그는 몸인 교회의 머리이며 시초이고 죽은 사람들 가운데서 처음 일으킴 받은 이시니 이는 친히 만유 가운데 첫머리가 되려 하심이다."
                },
                {
                    "verse": 19,
                    "text": "그러므로 하나님의 모든 충만이 그분 안에 기꺼이 거하며"
                },
                {
                    "verse": 20,
                    "text": "또 그의 십자가의 피로 평화를 이루어 그로 말미암아 만물 곧 땅 우의 것들이나 하늘의 것들이 모두 자신과 화해하게 하셨다."
                },
                {
                    "verse": 21,
                    "text": "너희는 한 때 악한 행실을 일삼으며 마음으로 하나님을 떠나 적대자들이었으나"
                },
                {
                    "verse": 22,
                    "text": "지금은 그가 친히 죽으심으로써 그 육의 몸으로 화친을 이루셨으니 이는 너희를 거룩하고 흠 없고 순결한 사람들로 자기 앞에 세우려 하심이다."
                },
                {
                    "verse": 23,
                    "text": "만일 너희가 든든하고 굳세게 믿음 가운데 계속 머물러 너희가 들은 바 그 복음의 소망에서 떠나 밀려다니지 아니하면 그리 행하실 것이다. 이 복음은 너희가 들은 것이요 또 하늘 아래 모든 피조물에게 전파되었거니와 나 바울은 이 복음의 일군이 되었다."
                },
                {
                    "verse": 24,
                    "text": "지금 나는 너희를 위한 나의 고난 가운데서 기뻐하며 그리스도의 고난의 덜 채워진 몫을 그의 몸을 위해 내 육체에 대신 채우고 있으니 그 몸은 곧 교회이다."
                },
                {
                    "verse": 25,
                    "text": "내가 그 교회의 일군이 되어 너희를 위해 내게 맡겨진 거룩한 직분에 따라 하나님의 뜻을 온전히 알리려고 하였다."
                },
                {
                    "verse": 26,
                    "text": "이 비밀은 여러 영원 여러 세대 동안 감추어져 있었으나 이제 비로소 성도들에게 알려졌다."
                },
                {
                    "verse": 27,
                    "text": "하나님이 이방인들 사이에서 이 비밀의 영광스런 부요가 얼마나 큰 것인지를 그들에게 알리기로 작정하셨으니 이 비밀은 바로 너희 가운데 계신 그리스도 곧 영광의 소망이시다."
                },
                {
                    "verse": 28,
                    "text": "우리가 온갖 지혜로 모든 사람을 경책하고 또 모든 사람을 가르치며 그를 선포하는 목적은 모든 사람을 그리스도 안에서 온전히 세우려는 것이다."
                },
                {
                    "verse": 29,
                    "text": "이를 목표로 나는 그가 내 안에 힘차게 불어넣으시는 동력을 모두 기울여 애쓰고 로력한다."
                }
            ]
        },
        {
            "chapter": 2,
            "verses": [
                {
                    "verse": 1,
                    "text": "그러므로 내가 얼마나 너희 곧 라오디게아에 있는 이들과 또 아직껏 나를 육신의 얼굴로 본 적이 없는 이들을 위해 애쓰고 있는지를 너희가 알아주기 바란다."
                },
                {
                    "verse": 2,
                    "text": "이는 그들의 마음이 북돋움을 얻고 사랑 안에서 깨우침을 얻게 하려는 것이며 이로써 그들이 충만한 깨달음의 온전한 부요를 누리고 나아가 하나님의 비밀 곧 그리스도를 알게 하려는 것이니"
                },
                {
                    "verse": 3,
                    "text": "그분 안에는 지혜와 지식의 온갖 보화들이 감추어져 있다."
                },
                {
                    "verse": 4,
                    "text": "내가 이것을 말하는 목적은 아무도 너희를 달콤한 말로 속여 꾀지 못하게 하려는 것이다."
                },
                {
                    "verse": 5,
                    "text": "그러므로 내가 비록 육으로는 떨어져 있으나 오히려 령으로는 너희와 함께 있으며 또 너희의 단정한 삶과 그리스도 안에서 너희의 믿음의 견고함을 보고 기뻐하는 바이다."
                },
                {
                    "verse": 6,
                    "text": "이제 너희가 그리스도 예수를 주로 영접하였으니 그렇게 그분 안에서 살아가되"
                },
                {
                    "verse": 7,
                    "text": "너희가 가르침받은 그대로 그분 안에 뿌리내리고 지어 올려지며 믿음으로 세워지고 감사에 풍성해지기 바란다."
                },
                {
                    "verse": 8,
                    "text": "어떤 사람이 그리스도를 따르지 않고 사람의 전통 곧 세상의 원시종교를 따라 철학이나 속 빈 속임수로써 너희를 사로잡지 못하도록 너희는 깨어 있으라."
                },
                {
                    "verse": 9,
                    "text": "사실 그리스도 안에는 신성의 온전한 충만이 몸으로 거하시니"
                },
                {
                    "verse": 10,
                    "text": "너희도 그분 안에서 충만함을 입었거니와 그는 모든 권세와 권위의 머리이시다."
                },
                {
                    "verse": 11,
                    "text": "그분 안에서 너희는 또한 손으로 행해지지 않은 할례로 베임 받았으니 곧 그리스도의 할례로 육의 몸을 벗어버렸다."
                },
                {
                    "verse": 12,
                    "text": "또 너희는 세례로 그와 함께 장사 되었으니 그 안에서 또한 그를 죽은 사람들 가운데서 살리신 하나님의 능력을 믿는 믿음으로 그와 함께 일으킴 받을 것이다."
                },
                {
                    "verse": 13,
                    "text": "그리고 너희가 아직 너희의 허물들과 너희의 죄투성이 본성의 비할례 가운데서 죽어 있을 동안에 하나님이 너희를 그리스도와 함께 사는 사람들로 만드시되 우리의 모든 죄과들을 사면하심으로써"
                },
                {
                    "verse": 14,
                    "text": "할례의 법 규범으로 우리에게 맞서왔던 그 손으로 쓴 증서를 지워 버리셨으니 곧 그것을 십자가에 못 박으심으로써 이 할례를 없애 버리신 것이다."
                },
                {
                    "verse": 15,
                    "text": "하나님이 모든 왕과 권세자들을 벌거벗겨 군중 앞에 웃음거리로 만드셨으니 곧 그리스도 안에서 그들을 누르고 개선하심이다."
                },
                {
                    "verse": 16,
                    "text": "그러므로 아무도 먹는 것이나 마시는 것이나 종교 축제나 새 달 경축이나 안식일 등의 문제로 너희를 판단하지 못하게 하라."
                },
                {
                    "verse": 17,
                    "text": "이것들은 앞으로 올 일들의 그림자일 뿐이나 그 실상은 그리스도이시다."
                },
                {
                    "verse": 18,
                    "text": "아무도 마음 낮추기와 천사숭배를 내세우면서 너희를 하찮게 여기지 못하게 하라. 그는 자신이 본 이상들을 떠벌리고 육의 생각을 바탕으로 헛되이 우쭐거리고"
                },
                {
                    "verse": 19,
                    "text": "머리를 붙들지 않거니와 그 머리로부터 온몸이 관절과 힘줄에 의해 공급받고 어우러지며 하나님께서 자라게 하심으로 자라간다."
                },
                {
                    "verse": 20,
                    "text": "사실 너희는 그리스도와 함께 세상의 원시적인 령들에 대해 죽었거늘 어찌하여 여전히 세상에 속해 사는 사람들같이 틀에 얽매이느냐."
                },
                {
                    "verse": 21,
                    "text": "너희는 만지지도 말고 맛보지도 말고 건드리지도 말라 라고 이르셨으니"
                },
                {
                    "verse": 22,
                    "text": "이는 쓸모가 다하여 깡그리 소멸될 것들 곧 인간의 계명과 교훈에 의한 규범들을 가리킴이 아니냐."
                },
                {
                    "verse": 23,
                    "text": "이러한 규범들은 엄격한 경건과 마음 낮추기와 몸을 다루는 고행 등으로 지혜의 모양을 갖추고 있으나 몸의 방종을 길들이는 데는 아무 가치도 없다."
                }
            ]
        },
        {
            "chapter": 3,
            "verses": [
                {
                    "verse": 1,
                    "text": "이제 너희는 그리스도와 함께 일으킴 받았으니 우에 있는 것을 찾으라. 거기에는 그리스도께서 하나님의 오른쪽에 앉아 계신다."
                },
                {
                    "verse": 2,
                    "text": "너희는 땅의 것들에 마음 두지 말고 오직 우에 있는 것들에 마음 두라."
                },
                {
                    "verse": 3,
                    "text": "사실 너희는 죽었고 또 너희의 생명은 그리스도와 함께 하나님 안에 감추인 바 되었다."
                },
                {
                    "verse": 4,
                    "text": "바야흐로 우리의 생명이신 그리스도께서 나타나시면 그때에 너희도 그와 함께 영광 중에 나타날 것이다."
                },
                {
                    "verse": 5,
                    "text": "그러므로 너희는 너희 안에 있는 땅의 본성을 죽일지니 이는 곧 음란과 더러움과 욕정과 야욕과 탐심 곧 우상숭배이다."
                },
                {
                    "verse": 6,
                    "text": "이런 행실들 때문에 하나님의 진노가 불순종의 아들들 우에 내려 온다."
                },
                {
                    "verse": 7,
                    "text": "너희도 한 때 그 행실들 가운데서 생활하였으니 그때에 너희는 그 가운데서 살아갔다."
                },
                {
                    "verse": 8,
                    "text": "그러나 이제 너희는 그 모든 것들 곧 노여움과 복수심과 원한과 비방과 더러운 말을 너희의 입술에서 모두 내어버리라."
                },
                {
                    "verse": 9,
                    "text": "너희가 옛사람과 함께 그 행습을 벗어버렸으니 서로에게 거짓말하지 말고"
                },
                {
                    "verse": 10,
                    "text": "오히려 새사람을 입을지니 새사람은 창조주의 형상을 따르는 지식 안에서 새롭게 지어져간다."
                },
                {
                    "verse": 11,
                    "text": "이제는 더 이상 헬라인이나 유대인 할례자나 무할례자 야만인이나 스구도인 노예나 자유인이 존재하지 않고 오직 그리스도께서 만유로서 만유 안에 계신다."
                },
                {
                    "verse": 12,
                    "text": "그러므로 너희는 하나님께 가려뽑힌 거룩하고 사랑받는 자녀들이니 동정과 친절과 겸손과 온유와 오래 참음을 갖춰"
                },
                {
                    "verse": 13,
                    "text": "서로 용서하라. 누구든지 다른 사람에게 탓할 일이 있으면 서로 용서할지니 주께서 너희를 용서하신 것같이 너희도 용서해야 한다."
                },
                {
                    "verse": 14,
                    "text": "또 이 모든 덕들 우에 너희는 사랑을 더할지니 이것은 온전한 화합의 띠이다."
                },
                {
                    "verse": 15,
                    "text": "너희의 마음에 그리스도의 평화가 자리잡게 할지니 이는 너희가 한 몸 안에서 이 평화에로 부름 받았기 때문이다."
                },
                {
                    "verse": 16,
                    "text": "그리스도의 말씀이 너희 안에 풍성히 거하도록 힘쓰고 온전한 지혜로 서로가 서로를 가르치며 일깨우고 감사에 찬 시와 찬양과 령감어린 노래들로 너희의 중심에서 하나님을 찬송하라."
                },
                {
                    "verse": 17,
                    "text": "그리고 말에나 일에나 무엇을 행하든지 너희는 모든 것을 주 예수의 이름으로 행하고 그를 통해 하나님 아버지께 감사를 드리라."
                },
                {
                    "verse": 18,
                    "text": "안해들아 남편들에게 복종할지니 이것이 주 안에서 마땅하다."
                },
                {
                    "verse": 19,
                    "text": "남편들아 안해들을 사랑하고 그들에게 성내지 말라."
                },
                {
                    "verse": 20,
                    "text": "자녀들아 너희의 부모에게 모든 일에 순종할지니 이것이 주를 기쁘시게 한다."
                },
                {
                    "verse": 21,
                    "text": "아비들아 너희의 자녀를 윽박지르지 말지니 이는 그들이 주눅들까 함이라."
                },
                {
                    "verse": 22,
                    "text": "종들아 육체의 주인들에게 모든 일에 순종하되 단지 사람에게 아부하듯 눈가림하지 말고 주를 경외하듯 순전한 마음으로 순종하라."
                },
                {
                    "verse": 23,
                    "text": "너희는 무슨 일을 행하든지 사람들이 아니라 주를 섬기는 것같이 성심으로 행할지니"
                },
                {
                    "verse": 24,
                    "text": "이는 너희가 주께로부터 유업을 상급으로 받게 될 것을 우리가 알기 때문이다. 너희는 주 되신 그리스도를 섬기고 있다."
                },
                {
                    "verse": 25,
                    "text": "그러므로 불의를 행하는 이는 그 행한바 불의를 돌려받으리니 불공정이 없을 것이다."
                }
            ]
        },
        {
            "chapter": 4,
            "verses": [
                {
                    "verse": 1,
                    "text": "주인들아 너희의 종들을 의롭고 공정하게 대하되 너희도 하늘에 한 주를 모시고 있음을 알라."
                },
                {
                    "verse": 2,
                    "text": "너희는 기도에 항상 힘쓰고 감사함으로 기도 중에 깨어 있으라."
                },
                {
                    "verse": 3,
                    "text": "또 너희는 우리를 위해서도 대신 빌되 하나님이 우리의 전도의 문을 열어 주시므로 우리가 그리스도의 비밀을 선포하도록 기도할지니 이를 위해 내가 사슬에 매어 있다."
                },
                {
                    "verse": 4,
                    "text": "너희는 내가 그 비밀을 알릴 수 있도록 기도할지니 이것은 나의 의무이다."
                },
                {
                    "verse": 5,
                    "text": "너희는 바깥사람들에게 지혜롭게 처신하되 기회를 살리라."
                },
                {
                    "verse": 6,
                    "text": "너희의 언사를 소금으로 고르어 은혜롭게 만들라. 그리하면 너희가 각 사람에게 어떻게 답변해야 하는지 알 수 있을 것이다."
                },
                {
                    "verse": 7,
                    "text": "두기고가 나의 일들을 모두 너희에게 이야기할 것인데 그는 사랑받는 형제이며 주 안에서 신실한 일군이요 함께 섬기는 종이다."
                },
                {
                    "verse": 8,
                    "text": "내가 그를 너희에게 보내는 것은 이 한 가지를 위함이니 곧 너희로 하여금 우리가 어떻게 지내는지 알게 하고 또 그로 하여금 너희의 마음을 북돋우게 하려는 것이다."
                },
                {
                    "verse": 9,
                    "text": "그와 함께 신실하고 사랑받는 형제 오네시모를 보내는데 그는 너희 회중의 일원이다. 그들이 여기서 일어나는 모든 일을 너희에게 이야기할 것이다."
                },
                {
                    "verse": 10,
                    "text": "옥중 동료 아리스다고가 너희에게 문안하고 바나바의 사촌 형제인 마가도 문안한다. 너희는 그에 관한 소식을 이미 들었을 것이다. 그가 너희에게 오면 너희는 그를 반겨 맞으라."
                },
                {
                    "verse": 11,
                    "text": "유스도라 불리는 예수도 너희에게 문안인사를 보낸다. 하나님 나라를 위한 나의 동료 일군들 가운데 이들만이 할례 받은 사람들인데 그들은 내게 위로가 되었다."
                },
                {
                    "verse": 12,
                    "text": "너희 회중의 일원이며 그리스도 예수의 일군인 에바브라가 너희에게 문안한다. 그는 너희를 위한 기도 가운데서 복음을 위해 힘쓰고 있으니 이는 너희로 굳건히 서서 하나님의 온전한 뜻 가 운데서 충만함을 입게 하려는 것이다."
                },
                {
                    "verse": 13,
                    "text": "그러므로 내가 그를 위해 증언할 수 있으니 그는 너희와 및 라오디게아와 히에라볼리에 있는 이들을 위해 힘써 일하고 있다."
                },
                {
                    "verse": 14,
                    "text": "사랑받는 의사 누가가 데마와 함께 너희에게 문안한다."
                },
                {
                    "verse": 15,
                    "text": "라오디게아에 있는 형제들과 눔바와 그녀의 집에 있는 교회에도 나의 문안인사를 전하라."
                },
                {
                    "verse": 16,
                    "text": "이 편지가 너희들 사이에서 돌려 읽혀진 후에 라오디게아의 회중에서도 읽혀지게 하고 그 다음에 너희는 라오디게아에서 온 편지를 읽도록 하라."
                },
                {
                    "verse": 17,
                    "text": "너희는 아깁보에게 주 안에서 네가 받은 직분을 완수하도록 힘쓰라고 전하라"
                },
                {
                    "verse": 18,
                    "text": "나 바울은 이 인사말을 나의 친필로 쓴다. 너희는 나의 죄수된 것을 기억하라. 너희에게 은혜가."
                }
            ]
        }
    ]
}