{
    "book": "디도서",
    "bookEn": "Titus",
    "abbr": "Tit",
    "chapters": [
        {
            "chapter": 1,
            "verses": [
                {
                    "verse": 1,
                    "text": "하나님의 종이며 예수 그리스도의 사도인 바울은 하나님이 택하신 이들의 믿음과 경건에 이르는 진리의 지식에 따라"
                },
                {
                    "verse": 2,
                    "text": "영원한 생명의 소망 가운데 있으니 이 영원한 생명은 거짓말하실 수 없는 하나님이 세계 창조 이전에 미리 약속하신 것이다."
                },
                {
                    "verse": 3,
                    "text": "그러나 하나님이 작정하신 기간에 전도로써 그의 말씀을 나타내셨는데 이 전도의 사명이 우리의 구원자이신 하나님의 명령에 의해 내게 위임되었다."
                },
                {
                    "verse": 4,
                    "text": "공동체의 믿음 안에서 참 아들 된 디도에게 편지하는데 하나님 아버지와 우리의 구원자 그리스도 예수로부터 은혜와 평화가 그대에게."
                },
                {
                    "verse": 5,
                    "text": "내가 너를 그레데에 남겨 둔 까닭은 이것이니 내가 네게 지시한 대로 덜 매듭지어진 일들을 올바로 매듭짓고 도시마다 교회의 어른을 세우려 함이었다."
                },
                {
                    "verse": 6,
                    "text": "누구든지 어른은 나무랄 데가 없어야 하고 한 안해의 지아비로서 그 자녀들이 방탕하다거나 고분고분하지 않다고 비난받지 않는 믿는 자녀를 둔 사람이어야 한다."
                },
                {
                    "verse": 7,
                    "text": "감독은 하나님의 살림군으로서 나무랄 데가 없어야 하며 스스로 잘난 사람이나 성질 사나운 사람이나 술고래나 싸움군이나 눈먼 돈을 밝히는 사람은 삼가야 하고"
                },
                {
                    "verse": 8,
                    "text": "오직 친절한 사람과 선행을 즐기는 사람과 마음을 길들인 사람과 정의로운 사람과 경건한 사람과 자제력을 갖춘 사람으로서"
                },
                {
                    "verse": 9,
                    "text": "그 배운바 그대로 믿음의 도를 굳게 붙들고 있는 사람이라야 하리니 그래야만 그가 건전한 가르침으로 교훈을 베풀 수 있고 또 그 가르침에 어긋나는 이들을 꾸짖을 수 있을 것이다."
                },
                {
                    "verse": 10,
                    "text": "특히 할례파에 불순종과 공허한 말과 속임수를 일삼는 이가 많은데"
                },
                {
                    "verse": 11,
                    "text": "이들은 더럽고 누추한 소득을 노리고 마땅하지 않은 것을 가르쳐 가정들을 모두 뒤엎으니 너는 그들로 입 다물게 만들어야 한다."
                },
                {
                    "verse": 12,
                    "text": "그들 중의 한 사람 곧 그들 분파의 대언자 하나가 그레데인들은 언제나 거짓말쟁이요 사나운 짐승이요 게으른 먹보 라고 말하였다."
                },
                {
                    "verse": 13,
                    "text": "그 증언은 참되니 너는 그러므로 그들을 따끔하게 꾸짖어 그들로 믿음 안에서 건전해지게 하고"
                },
                {
                    "verse": 14,
                    "text": "또 유대인의 신화나 진리를 거부하는 사람의 계명에 한 눈 팔지 못하게 하라."
                },
                {
                    "verse": 15,
                    "text": "깨끗한 사람에게는 만물이 모두 깨끗하나 얼룩지고 아니 믿는 사람에게는 오히려 그 마음과 량심이 얼룩져 있어 아무것도 깨끗하지 않다."
                },
                {
                    "verse": 16,
                    "text": "그들이 하나님을 안다고 주장하나 행위로 하나님을 부인하니 그들은 혐오스럽고 완고하고 선한 행실을 하지 않는다."
                }
            ]
        },
        {
            "chapter": 2,
            "verses": [
                {
                    "verse": 1,
                    "text": "그러나 너는 진실한 교훈에 걸맞는 강론을 베풀라."
                },
                {
                    "verse": 2,
                    "text": "너는 나이 든 아버지들에게 단정하고 근엄하고 사려 깊고 믿음과 사랑과 인내에 건실해지도록 명하라."
                },
                {
                    "verse": 3,
                    "text": "너는 나이 든 어머니들에게 역시 그 행실에 경건해지고 험담군이나 술군이 되지 않도록 명하라. 오히려 그들로 하여금 무엇이 선인지 가르치되"
                },
                {
                    "verse": 4,
                    "text": "젊은 녀인들을 훈련하여 그 남편과 자녀를 사랑하게 하고"
                },
                {
                    "verse": 5,
                    "text": "사려 깊고 정숙하고 가정에 충실하고 선량하고 남편들에게 온순하게 만들지니 이는 하나님의 도가 훼손되지 않게 하려는 것이다."
                },
                {
                    "verse": 6,
                    "text": "이와 같이 너는 젊은 남자들을 타일러 스스로를 다스리게 하라."
                },
                {
                    "verse": 7,
                    "text": "너는 스스로 모든 면에서 선한 행실을 본 보이되 너의 가르침에서 성실과 위엄을 보이고"
                },
                {
                    "verse": 8,
                    "text": "또 조금도 나무랄 데 없는 건실한 언사를 보여 주고 이로써 우리에 대해 비난할 여지를 아예 없애 오히려 반대자가 부끄러운 지경에 놓이게 하라."
                },
                {
                    "verse": 9,
                    "text": "너는 종들을 타일러 그 주인들에게 순종하여 모든 면에서 만족을 주게 하라. 종들은 고집 부리거나"
                },
                {
                    "verse": 10,
                    "text": "훔치지 말고 오히려 온전하고 참된 충성을 보여야 할지니 이로써 그들은 우리의 구원자이신 하나님의 가르침을 모든 면에서 아름답게 만들 것이다."
                },
                {
                    "verse": 11,
                    "text": "그러므로 만민의 구주이신 하나님의 은혜가 나타나"
                },
                {
                    "verse": 12,
                    "text": "우리를 훈련하여 우리로 하여금 불경건과 세속의 정욕들을 끊어 버리고 이 세대에서 단정하고 올바르고 경건하게 살아가며"
                },
                {
                    "verse": 13,
                    "text": "그 복된 소망 곧 우리의 크신 하나님과 구원자 예수 그리스도의 영광이 나타날 것을 기다리게 하셨으니"
                },
                {
                    "verse": 14,
                    "text": "예수는 모든 사악에서 우리를 건져내고 또 그분 자신을 위해 선한 행실에 뜨겁게 힘쓰는 그의 친 백성을 성별하려고 우리를 위해 자기 몸을 내어 주셨다."
                },
                {
                    "verse": 15,
                    "text": "너는 이 내용들을 강론하되 온전한 권위로 타이르고 꾸짖을 것이며 아무도 너를 업신여기지 못하게 하라."
                }
            ]
        },
        {
            "chapter": 3,
            "verses": [
                {
                    "verse": 1,
                    "text": "너는 그들을 일깨워 령도자들과 권세자들에게 복종하며 순종하게 하고 모든 선한 일에 대비하게 하고"
                },
                {
                    "verse": 2,
                    "text": "아무에게도 비난받지 않게 하고 말다툼하지 않게 하되 오히려 온유하게 되어 모든 이들에게 정중한 례절을 보이게 하라."
                },
                {
                    "verse": 3,
                    "text": "사실 우리 자신도 한 때는 어리석고 검질기고 빗나가서 온갖 정욕과 향락의 노예로서 악의와 시샘 가운데서 나날을 보내며 사람들에게 미움을 사고 또 서로 미워하였다."
                },
                {
                    "verse": 4,
                    "text": "그러나 바야흐로 우리의 구원자이신 하나님의 선하심과 인자하심이 나타나"
                },
                {
                    "verse": 5,
                    "text": "그가 우리를 구원하셨으니. 이는 우리에 의해 의로 행해진 행실들 때문이 아니고 오직 그 분 자신의 자비 덕분이며 성령 안에서 거듭남과 새롭게 하심의 씻음으로 말미암은 것이다."
                },
                {
                    "verse": 6,
                    "text": "하나님은 우리의 구원자 예수 그리스도를 통해 우리 우에 이 성령을 넘치도록 부어 주시고"
                },
                {
                    "verse": 7,
                    "text": "우리가 이로써 그의 은혜로 의롭다 하심을 얻게 하시고 또 영원한 소망의 상속자들이 되게 하셨다."
                },
                {
                    "verse": 8,
                    "text": "미쁘다 이 말이여. 나는 네가 이 내용을 역설하기 원하는데 이는 하나님을 이미 믿은 사람들이 마음을 다잡아 선한 일들을 힘써 행하게 하려는 것이다. 이 일들은 선하며 또 사람들에게 유익하다."
                },
                {
                    "verse": 9,
                    "text": "그러나 너는 어리석은 토론이나 족보이야기나 다툼이나 률법에 관한 론쟁을 피하라. 사실 이런 일들은 유익하지 않고 무익하다."
                },
                {
                    "verse": 10,
                    "text": "파당군의 경우 너는 그를 한 두 번 경고한 후에 그와 더 관계하지 말라."
                },
                {
                    "verse": 11,
                    "text": "네가 아는 바대로 그러한 사람은 뒤틀리고 죄에 물들었으니 스스로 정죄 받는다."
                },
                {
                    "verse": 12,
                    "text": "내가 아데마나 두기고를 네게로 보냈으니 너는 서둘러 내게로 오되 니고볼리로 향하라. 이는 내가 거기서 겨울을 나려고 마음먹었기 때문이다."
                },
                {
                    "verse": 13,
                    "text": "너는 서둘러 률법교사 세나와 아볼로를 먼저 보내고 그들이 아무 것도 모자라지 않도록 배려하라."
                },
                {
                    "verse": 14,
                    "text": "그리고 우리 사람들로 하여금 스스로 선한 일들에 앞장서는 법을 배우게 하고 이로써 꼭 필요한 선행에 힘써서 열매 없는 사람들이 되지 않게 하라."
                },
                {
                    "verse": 15,
                    "text": "나와 함께 있는 이들이 모두 네게 문안한다. 믿음 안에서 우리를 사랑하는 모든 이들에게 너는 문안하라. 너희 모두에게 은혜가."
                }
            ]
        }
    ]
}